mlpylib/__init__.py
mlpylib/interface.py
mlpylib/_mlops_platform/__init__.py
mlpylib/_mlops_platform/interface.py
mlpylib/_mlops_platform/mlflowhandler.py
mlpylib/_mlrunparameter/__init__.py
mlpylib/_mlrunparameter/mlrunparameterkeys.py
mlpylib/_mlrunparameter/mlrunparameters.py
mlpylib/_util/__init__.py
mlpylib/_util/code.py
mlpylib/_util/gitutil.py
mlpylib/_util/logging.py
mlpylib/_util/nomenclature.py
mlpylib/entity/__init__.py
mlpylib/entity/releaseinfo.py
example_package_yule-1.0.1.dist-info/LICENSE
example_package_yule-1.0.1.dist-info/METADATA
example_package_yule-1.0.1.dist-info/WHEEL
example_package_yule-1.0.1.dist-info/top_level.txt
example_package_yule-1.0.1.dist-info/RECORD
